LICENSE
README.rst
setup.py
py2html/__init__.py
py2html/_html.py
py2html/elements/__init__.py
py2html/elements/attributes.py
py2html/elements/elements.py
py2html/ext/__init__.py
py2html/ext/_helper.py
py2html/ext/ext_element.py
py2html/ext/ext_utils.py
py2html/ext/script.py
py2html/ext/style.py
pytohtml.egg-info/PKG-INFO
pytohtml.egg-info/SOURCES.txt
pytohtml.egg-info/dependency_links.txt
pytohtml.egg-info/top_level.txt