Metadata-Version: 2.1
Name: pytohtml
Version: 1.2.4
Summary: Write HTML with Pythonic Code
Home-page: https://github.com/am230/py2html
Author: am230
Author-email: am.230@outlook.jp
License: MIT Licence
Keywords: html,pythonic
Platform: any
Requires: strbuilder
Requires: Flask
Requires: libsass
License-File: LICENSE
